pyalgen/__init__.py
pyalgen/crossover.py
pyalgen/genetic.py
pyalgen/mutation.py
pyalgen/population.py
pyalgen/selection.py
pyalgen/test_functions.py
pyalgen-0.0.6.dist-info/METADATA
pyalgen-0.0.6.dist-info/WHEEL
pyalgen-0.0.6.dist-info/top_level.txt
pyalgen-0.0.6.dist-info/RECORD
