Metadata-Version: 2.1
Name: pyalgen
Version: 0.0.6
Summary: Minimal python library for genetic algorithm
Home-page: https://github.com/amalshaji/pyalgen
Author: Amal Shaji
Author-email: amalshajid@gmail.com
License: MIT
Platform: UNKNOWN
Classifier: License :: OSI Approved :: MIT License
Classifier: Programming Language :: Python :: 3
Classifier: Programming Language :: Python :: 3.8
Requires-Dist: numpy
Requires-Dist: tqdm
